php2json.so
php2json-0.2.dist-info/RECORD
php2json-0.2.dist-info/METADATA
php2json-0.2.dist-info/WHEEL
php2json-0.2.dist-info/top_level.txt
php2json-0.2.dist-info/metadata.json
php2json-0.2.dist-info/DESCRIPTION.rst
