Metadata-Version: 2.0
Name: php2json
Version: 0.2
Summary: Convert PHP serializer strings to JSON
Home-page: https://github.com/mbachry/php2json
Author: Marcin Bachry
Author-email: hegel666@gmail.com
License: MIT
Platform: UNKNOWN
Classifier: Development Status :: 4 - Beta
Classifier: Intended Audience :: Developers
Classifier: License :: OSI Approved :: MIT License
Classifier: Natural Language :: English
Classifier: Programming Language :: Python :: 2
Classifier: Programming Language :: Python :: 2.7
Classifier: Programming Language :: Python :: 3
Classifier: Programming Language :: Python :: 3.6
